sgex/__init__.py
sgex/call.py
sgex/job.py
sgex/query.py
sgex/util.py
sgex-0.7.5.dist-info/LICENSE
sgex-0.7.5.dist-info/METADATA
sgex-0.7.5.dist-info/WHEEL
sgex-0.7.5.dist-info/top_level.txt
sgex-0.7.5.dist-info/RECORD
