Metadata-Version: 2.1
Name: sgex
Version: 0.7.5
Summary: Sketch Grammar Explorer (Sketch Engine API wrapper)
Author-email: Loryn Isaacs <50170623+engisalor@users.noreply.github.com>
License: BSD 3-Clause License
Project-URL: repository, https://github.com/engisalor/sketch-grammar-explorer.git
Keywords: sketch engine,api wrapper,corpus linguistics,text analysis,natural language processing
Classifier: Development Status :: 4 - Beta
Classifier: Programming Language :: Python :: 3.11
Classifier: License :: OSI Approved :: BSD License
Classifier: Operating System :: OS Independent
Classifier: Topic :: Text Processing :: Linguistic
Classifier: Topic :: Scientific/Engineering :: Information Analysis
Requires-Python: >=3.11
License-File: LICENSE
Requires-Dist: aiofiles
Requires-Dist: aiohttp
Requires-Dist: pandas
Requires-Dist: pyyaml
